agile_mcp/__init__.py
agile_mcp/__main__.py
agile_mcp/server.py
agile_mcp/models/__init__.py
agile_mcp/models/base.py
agile_mcp/models/dependency.py
agile_mcp/models/epic.py
agile_mcp/models/sprint.py
agile_mcp/models/story.py
agile_mcp/models/task.py
agile_mcp/schemas/agile_documentation_schema.json
agile_mcp/services/__init__.py
agile_mcp/services/config_service.py
agile_mcp/services/dependency_service.py
agile_mcp/services/epic_service.py
agile_mcp/services/project_status_service.py
agile_mcp/services/sprint_service.py
agile_mcp/services/story_service.py
agile_mcp/services/task_service.py
agile_mcp/storage/__init__.py
agile_mcp/storage/filesystem.py
agile_mcp/tools/__init__.py
agile_mcp/tools/base.py
agile_mcp/tools/burndown_chart_tool.py
agile_mcp/tools/dependency_tools.py
agile_mcp/tools/documentation_tools.py
agile_mcp/tools/epic_tools.py
agile_mcp/tools/overview_tools.py
agile_mcp/tools/project_tools.py
agile_mcp/tools/sprint_tools.py
agile_mcp/tools/story_tools.py
agile_mcp/tools/task_tools.py
agile_mcp/utils/__init__.py
agile_mcp/utils/id_generator.py
agile_mcp_server-0.4.0.dist-info/METADATA
agile_mcp_server-0.4.0.dist-info/WHEEL
agile_mcp_server-0.4.0.dist-info/entry_points.txt
agile_mcp_server-0.4.0.dist-info/RECORD
