Metadata-Version: 2.4
Name: agile-mcp-server
Version: 0.4.0
Summary: An Agile Project Management MCP Server that transforms LLMs into powerful agile assistants
Project-URL: Homepage, https://github.com/agile-mcp/agile-mcp-server
Project-URL: Documentation, https://agile-mcp.readthedocs.io/
Project-URL: Repository, https://github.com/agile-mcp/agile-mcp-server
Project-URL: Bug Tracker, https://github.com/agile-mcp/agile-mcp-server/issues
Author-email: Agile MCP Team <team@agile-mcp.com>
License: MIT
Keywords: agile,kanban,llm,mcp,project-management,scrum
Classifier: Development Status :: 3 - Alpha
Classifier: Intended Audience :: Developers
Classifier: License :: OSI Approved :: MIT License
Classifier: Programming Language :: Python :: 3
Classifier: Programming Language :: Python :: 3.10
Classifier: Programming Language :: Python :: 3.11
Classifier: Programming Language :: Python :: 3.12
Requires-Python: >=3.10
Requires-Dist: click>=8.0.0
Requires-Dist: docstring-parser>=0.15
Requires-Dist: mcp>=1.0.0
Requires-Dist: pathspec>=0.11.0
Requires-Dist: pydantic>=2.0.0
Requires-Dist: pyyaml>=6.0
